rdfcrate/__init__.py
rdfcrate/bioschemas.py
rdfcrate/codegen.py
rdfcrate/spec_version.py
rdfcrate/uris.py
rdfcrate/wrapper.py
rdfcrate-0.2.0.dist-info/METADATA
rdfcrate-0.2.0.dist-info/WHEEL
rdfcrate-0.2.0.dist-info/entry_points.txt
rdfcrate-0.2.0.dist-info/RECORD
