Metadata-Version: 2.4
Name: rdfcrate
Version: 0.2.0
Summary: Library for building RO-Crates using rdflib
Author-email: Michael Milton <michael.r.milton@gmail.com>
Requires-Python: >=3.10
Requires-Dist: rdflib>=7.1.2
